MANIFEST.in
requirements.txt
setup.py
baboon/__init__.py
baboon.egg-info/PKG-INFO
baboon.egg-info/SOURCES.txt
baboon.egg-info/dependency_links.txt
baboon.egg-info/requires.txt
baboon.egg-info/top_level.txt
baboon/baboon/__init__.py
baboon/baboon/commands.py
baboon/baboon/config.py
baboon/baboon/dictconf.py
baboon/baboon/fmt.py
baboon/baboon/initializor.py
baboon/baboon/main.py
baboon/baboon/monitor.py
baboon/baboon/transport.py
baboon/baboon/plugins/__init__.py
baboon/baboon/plugins/git/__init__.py
baboon/baboon/plugins/git/monitor_git.py
baboon/baboond/__init__.py
baboon/baboond/config.py
baboon/baboond/dictconf.py
baboon/baboond/dispatcher.py
baboon/baboond/executor.py
baboon/baboond/main.py
baboon/baboond/task.py
baboon/baboond/transport.py
baboon/common/__init__.py
baboon/common/config.py
baboon/common/eventbus.py
baboon/common/file.py
baboon/common/logger.py
baboon/common/loghandler.py
baboon/common/proxy_socket.py
baboon/common/pyrsync.py
baboon/common/utils.py
baboon/common/errors/__init__.py
baboon/common/errors/baboon_exception.py
baboon/common/stanza/__init__.py
baboon/common/stanza/rsync.py
baboon/common/thirdparty/__init__.py
baboon/common/thirdparty/dictconfig.py
baboon/conf/baboondrc
baboon/conf/baboonrc
bin/baboon
bin/baboond