Metadata-Version: 1.1
Name: baboon
Version: 0.1.4
Summary: Detect merge conflict in realtime.
Home-page: http://baboon-project.org
Author: Sandro Munda
Author-email: sandro@munda.me
License: MIT
Download-URL: https://github.com/SeyZ/baboon/tarball/master
Platform: UNKNOWN
Classifier: Development Status :: 5 - Production/Stable
Classifier: Environment :: Console
Classifier: Intended Audience :: Developers
Classifier: Intended Audience :: Information Technology
Classifier: License :: OSI Approved :: MIT License
Classifier: Operating System :: POSIX :: BSD
Classifier: Operating System :: POSIX :: Linux
Classifier: Operating System :: POSIX :: Other
Classifier: Programming Language :: Cython
Classifier: Programming Language :: Python
Classifier: Programming Language :: Python :: 2.6
Classifier: Programming Language :: Python :: 2.7
Classifier: Topic :: Software Development :: Quality Assurance
